{"assets/5-piso.jpg":["assets/5-piso.jpg"],"packages/cupertino_icons/assets/CupertinoIcons.ttf":["packages/cupertino_icons/assets/CupertinoIcons.ttf"],"assets/EdificioBelgrano.png":["assets/EdificioBelgrano.png"],"assets/catastro.png":["assets/catastro.png"],"assets/irpf.png":["assets/irpf.png"],"assets/iva.png":["assets/iva.png"],"assets/logo-footer.png":["assets/logo-footer.png"],"assets/logoMoebius.png":["assets/logoMoebius.png"],"assets/patrimonio.png":["assets/patrimonio.png"],"assets/plantabaja.jpg":["assets/plantabaja.jpg"],"assets/precio102-al-402.jpg":["assets/precio102-al-402.jpg"],"assets/precio103-203.jpg":["assets/precio103-203.jpg"],"assets/primero-y-segundo.jpg":["assets/primero-y-segundo.jpg"],"assets/render.jpeg":["assets/render.jpeg"],"assets/tercer-y-cuarto.jpg":["assets/tercer-y-cuarto.jpg"]}